tor_request/__init__.py
tor_request/base/__init__.py
tor_request/base/base_request_client.py
tor_request/clients/__init__.py
tor_request/clients/request_client.py
tor_request/clients/selenium_client.py
tor_request/controller/__init__.py
tor_request/controller/base/__init__.py
tor_request/controller/base/base_tor_controller.py
tor_request/controller/interfaces/__init__.py
tor_request/controller/interfaces/abstract_tor_controller.py
tor_request/controller/tor_control.py
tor_request/controller/utiles/__init__.py
tor_request/controller/utiles/renew_tor_ip.py
tor_request/interfaces/__init__.py
tor_request/interfaces/abstract_request_client.py
tor_request/types/__init__.py
tor_request/types/requests_client_config.py
tor_request/types/selenium_client_config.py
tor_request/types/selenium_client_scroll_config.py
tor_request/utiles/.DS_Store
tor_request/utiles/__init__.py
tor_request/utiles/chrome_driver_manager.py
tor_request/utiles/format_elapsed_time.py
tor_request/utiles/get_logger.py
tor_rq-0.0.5.dist-info/LICENSE
tor_rq-0.0.5.dist-info/METADATA
tor_rq-0.0.5.dist-info/WHEEL
tor_rq-0.0.5.dist-info/RECORD
