Metadata-Version: 2.3
Name: tor-rq
Version: 0.0.5
Summary: tor request is a Python package for making HTTP requests through the Tor network.
License: SEE LICENSE FILE
Author: minjun ju
Author-email: dev.mjun@gmail.com
Requires-Python: >=3.10,<4.0
Classifier: License :: Other/Proprietary License
Classifier: Programming Language :: Python :: 3
Classifier: Programming Language :: Python :: 3.10
Classifier: Programming Language :: Python :: 3.11
Classifier: Programming Language :: Python :: 3.12
Classifier: Programming Language :: Python :: 3.13
Classifier: Programming Language :: Python :: 3 :: Only
Requires-Dist: beautifulsoup4 (==4.13.3)
Requires-Dist: certifi (>=2025.4.26,<2026.0.0)
Requires-Dist: lxml[html-clean] (>=5.4.0,<6.0.0)
Requires-Dist: pysocks (>=1.7.1,<2.0.0)
Requires-Dist: requests[socks] (>=2.32.3,<3.0.0)
Requires-Dist: selenium (>=4.32.0,<5.0.0)
Requires-Dist: stem (>=1.8.2,<2.0.0)
Requires-Dist: tenacity (>=9.1.2,<10.0.0)
Requires-Dist: webdriver-manager (>=4.0.2,<5.0.0)
Project-URL: Homepage, https://github.com/devmjun/tor-request
Project-URL: Repository, https://github.com/devmjun/tor-request
